django_discordo/__init__.py
django_discordo/handler.py
django_discordo-1.0.0.dist-info/WHEEL
django_discordo-1.0.0.dist-info/METADATA
django_discordo-1.0.0.dist-info/RECORD
