Metadata-Version: 2.3
Name: django-discordo
Version: 1.0.0
Summary: Discord webhook handler for Django logging
Keywords: django,discord,logging,webhook,handler
Author: Evan Chen
Author-email: Evan Chen <evan@evanchen.cc>
License: MIT
Classifier: Development Status :: 4 - Beta
Classifier: Framework :: Django
Classifier: Framework :: Django :: 3.2
Classifier: Framework :: Django :: 4.0
Classifier: Framework :: Django :: 4.1
Classifier: Framework :: Django :: 4.2
Classifier: Framework :: Django :: 5.0
Classifier: Intended Audience :: Developers
Classifier: License :: OSI Approved :: MIT License
Classifier: Operating System :: OS Independent
Classifier: Programming Language :: Python
Classifier: Programming Language :: Python :: 3
Classifier: Programming Language :: Python :: 3.8
Classifier: Programming Language :: Python :: 3.9
Classifier: Programming Language :: Python :: 3.10
Classifier: Programming Language :: Python :: 3.11
Classifier: Programming Language :: Python :: 3.12
Classifier: Topic :: Software Development :: Libraries :: Python Modules
Classifier: Topic :: System :: Logging
Requires-Dist: requests>=2.25.0
Requires-Dist: django>=3.2 ; extra == 'django'
Requires-Python: >=3.8
Project-URL: Homepage, https://github.com/vEnhance/django-discordo
Project-URL: Issues, https://github.com/vEnhance/django-discordo/issues
Project-URL: Repository, https://github.com/vEnhance/django-discordo
Provides-Extra: django
